pyosmeta/__init__.py
pyosmeta/_version.py
pyosmeta/contributors.py
pyosmeta/file_io.py
pyosmeta/github_api.py
pyosmeta/logging.py
pyosmeta/parse_issues.py
pyosmeta/parse_rss.py
pyosmeta/utils_clean.py
pyosmeta/utils_parse.py
pyosmeta/cli/fetch_rss_feed.py
pyosmeta/cli/parse_history.py
pyosmeta/cli/process_reviews.py
pyosmeta/cli/update_contributors.py
pyosmeta/cli/update_review_teams.py
pyosmeta/models/__init__.py
pyosmeta/models/base.py
pyosmeta/models/github.py
pyosmeta-1.7.7.dist-info/METADATA
pyosmeta-1.7.7.dist-info/WHEEL
pyosmeta-1.7.7.dist-info/entry_points.txt
pyosmeta-1.7.7.dist-info/licenses/LICENSE
pyosmeta-1.7.7.dist-info/RECORD
