Metadata-Version: 2.4
Name: pyosmeta
Version: 1.7.7
Summary: Tools that update the pyOpenSci contributor and review metadata that is posted on our website
Project-URL: Homepage, https://github.com/pyopensci/pyosmeta/
Project-URL: Bug Reports, https://github.com/pyopensci/pyosmeta/issues
Project-URL: Source, https://github.com/pyopensci/pyosmeta/issues
Author-email: Leah Wasser <leah@pyopensci.org>
Maintainer-email: pyOpenSci <admin@pyopensci.org>
License: MIT
License-File: LICENSE
Classifier: Development Status :: 4 - Beta
Classifier: Intended Audience :: Developers
Classifier: License :: OSI Approved :: MIT License
Classifier: Programming Language :: Python :: 3 :: Only
Classifier: Programming Language :: Python :: 3.10
Classifier: Programming Language :: Python :: 3.11
Classifier: Topic :: Software Development :: Build Tools
Requires-Python: >=3.10
Requires-Dist: click
Requires-Dist: feedparser
Requires-Dist: pydantic>=2.0
Requires-Dist: python-dotenv
Requires-Dist: requests
Requires-Dist: ruamel-yaml>=0.17.21
Requires-Dist: tqdm
Requires-Dist: unidecode
Provides-Extra: dev
Requires-Dist: black; extra == 'dev'
Requires-Dist: flake8; extra == 'dev'
Requires-Dist: pre-commit; extra == 'dev'
Requires-Dist: pytest; extra == 'dev'
Requires-Dist: pytest-cov; extra == 'dev'
Requires-Dist: pytest-localserver; extra == 'dev'
Requires-Dist: pytest-mock; extra == 'dev'
